Metadata-Version: 2.1
Name: FirstGame
Version: 1.0.14
Author: spx220
Author-email: eric2173459@gmail.com
License: MIT
Keywords: spx,kpop,anime,FirstGame
Classifier: Programming Language :: Python :: 3
Classifier: License :: OSI Approved :: MIT License
Classifier: Operating System :: OS Independent
Requires-Python: >=3.6
License-File: LICENSE.txt
Requires-Dist: pygame ==2.5.2
Requires-Dist: pymysql ==1.1.0
Requires-Dist: pillow ==10.2.0
Requires-Dist: pyyaml ==6.0.1
